neuscitk.py
neuscitk-1.2.2.dist-info/LICENSE.txt
neuscitk-1.2.2.dist-info/METADATA
neuscitk-1.2.2.dist-info/WHEEL
neuscitk-1.2.2.dist-info/top_level.txt
neuscitk-1.2.2.dist-info/RECORD
