Metadata-Version: 2.1
Name: neuscitk
Version: 1.2.2
Summary: Toolkit for companion course to UW Neusci 30x courses
Home-page: https://github.com/jeremyschroeter/neuscitk
Author: Jeremy Schroeter
Author-email: jeremyschroeter@gmail.com
License-File: LICENSE.txt
Requires-Dist: numpy
Requires-Dist: scipy
Requires-Dist: scikit-learn
Requires-Dist: matplotlib
